demand_acep/__init__.py
demand_acep/config.py
demand_acep/create_db_schema.py
demand_acep/demand_acep.py
demand_acep/extract_data_to_csv.py
demand_acep/timescale_parallel_copy.py
demand_acep/version.py
demand_acep-0.0.2.dist-info/METADATA
demand_acep-0.0.2.dist-info/RECORD
demand_acep-0.0.2.dist-info/WHEEL
demand_acep-0.0.2.dist-info/top_level.txt
